LICENSE.txt
MANIFEST.in
README.rst
setup.py
uic920/__init__.py
uic920.egg-info/PKG-INFO
uic920.egg-info/SOURCES.txt
uic920.egg-info/dependency_links.txt
uic920.egg-info/top_level.txt