Metadata-Version: 1.0
Name: uic920
Version: 0.1.0
Summary: Self contained UIC 920-14 country definitions
Home-page: https://github.com/neilalbrock/python-uic920
Author: Neil Albrock
Author-email: neil@atomised.coop
License: MIT
Keywords: uic 920 country codes
Platform: UNKNOWN
Classifier: Development Status :: 4 - Beta
Classifier: License :: OSI Approved :: MIT License
Classifier: Intended Audience :: Developers
Classifier: Natural Language :: English
Classifier: Programming Language :: Python
